[
    {
        "id": 16,
        "id_contrato_marco": 1,
        "codigo_contrato_marco": 6700210138,
        "pedido": 3701688541,
        "contrato_marco": "TECHINT MOA x Volumen",
        "id_periodonumber": 16,
        "periodo": "Apr-19",
        "fecha_inicio_periodo": "3/25/2019",
        "fecha_fin_periodo": "4/21/2019",
        "id_certificacion_volume": 16,
        "id_certificacion_volumen_detalle": 2650,
        "id_estado": 39,
        "activo": 1,
        "fecha_registro": "12:07",
        "id_usuario_registro": 1,
        "id_consolidacion_volumen_detalle": 2568,
        "id_consolidacion_volumen": 16,
        "consolidacion_volumen": "Apr/19",
        "id_orden_trabajo_avance_detalle": 2669,
        "id_orden_trabajo": 57,
        "id_item": 24,
        "precio_estandar": 394.68,
        "item": "Bandejas hasta 2M",
        "codigo_item": "E211",
        "descripcion_compuesta": "(E211) Bandejas hasta 2M x MT - Elect.",
        "id_especialidad": 1,
        "especialidad": "Eléctrico",
        "std": 2.4,
        "id_unidad_medida": 3,
        "unidad_medida": "MT",
        "cantidad_volumen": 50.4,
        "monto_calculado": 19891.872,
        "id_posicion": 1,
        "id_subposicion": 706
    }
]